fead.py
fead-1.0.0.dist-info/entry_points.txt
fead-1.0.0.dist-info/COPYING
fead-1.0.0.dist-info/WHEEL
fead-1.0.0.dist-info/METADATA
fead-1.0.0.dist-info/RECORD
