Metadata-Version: 2.1
Name: fead
Version: 1.0.0
Summary: Advert generator from web feeds
Keywords: rss,atom
Author-email: Nguyễn Gia Phong <cnx@loang.net>, Ngô Ngọc Đức Huy <huyngo@disroot.org>
Maintainer-email: Nguyễn Gia Phong <~cnx/misc@lists.sr.ht>
Requires-Python: >=3.11
Classifier: Development Status :: 5 - Production/Stable
Classifier: Environment :: Console
Classifier: Framework :: AsyncIO
Classifier: License :: OSI Approved :: GNU Affero General Public License v3 or later (AGPLv3+)
Classifier: Operating System :: OS Independent
Classifier: Programming Language :: Python
Classifier: Topic :: Utilities
Project-URL: Source, https://trong.loang.net/~cnx/fead
